{
  "moroccan_cities": [
    {"id" : 0, "city" : "صخيرات"},
    {"id": 1, "city": "أصيلة"},
    {"id": 2, "city": "أغادير"},
    {"id": 3, "city": "إفران"},
    {"id": 4, "city": "ابن جرير"},
    {"id": 5, "city": "ابن سليمان"},
    {"id": 6, "city": "اسفي"},
    {"id": 7, "city": "اكادير"},
    {"id": 8, "city": "الجديدة"},
    {"id": 9, "city": "الحسيمة"},
    {"id": 10, "city": "الخميسات"},
    {"id": 11, "city": "الداخلة"},
    {"id": 12, "city": "الدار البيضاء"},
    {"id": 13, "city": "الرباط"},
    {"id": 14, "city": "الصويرة"},
    {"id": 15, "city": "العرائش"},
    {"id": 16, "city": "العيون"},
    {"id": 17, "city": "القصر الكبير"},
    {"id": 18, "city": "القنيطرة"},
    {"id": 19, "city": "المحمدية"},
    {"id": 20, "city": "الناظور"},
    {"id": 21, "city": "اليوسفية"},
    {"id": 22, "city": "اولاد تايمة"},
    {"id": 23, "city": "ايت ملول"},
    {"id": 24, "city": "بركان"},
    {"id": 25, "city": "برشيد"},
    {"id": 26, "city": "بني ملال"},
    {"id": 27, "city": "بوجدور"},
    {"id": 28, "city": "بوزنيقة"},
    {"id": 29, "city": "بولمان"},
    {"id": 30, "city": "تارودانت"},
    {"id": 31, "city": "تازة"},
    {"id": 32, "city": "تافراوت"},
    {"id": 33, "city": "تاونات"},
    {"id": 34, "city": "تزنيت"},
    {"id": 35, "city": "تطوان"},
    {"id": 36, "city": "تمارة"},
    {"id": 37, "city": "تنغير"},
    {"id": 38, "city": "جرسيف"},
    {"id": 39, "city": "جرادة"},
    {"id": 40, "city": "خريبكة"},
    {"id": 41, "city": "خنيفرة"},
    {"id": 42, "city": "دمنات"},
    {"id": 43, "city": "زاكورة"},
    {"id": 44, "city": "سطات"},
    {"id": 45, "city": "سلا"},
    {"id": 46, "city": "سوق السبت"},
    {"id": 47, "city": "سيدي إفني"},
    {"id": 48, "city": "سيدي بنور"},
    {"id": 49, "city": "سيدي قاسم"},
    {"id": 50, "city": "سيدي يحيى الغرب"},
    {"id": 51, "city": "شفشاون"},
    {"id": 52, "city": "صفرو"},
    {"id": 53, "city": "طانطان"},
    {"id": 54, "city": "طنجة"},
    {"id": 55, "city": "عين حرودة"},
    {"id": 56, "city": "فاس"},
    {"id": 57, "city": "فكيك"},
    {"id": 58, "city": "قلعة السراغنة"},
    {"id": 59, "city": "كلميم"},
    {"id": 60, "city": "مراكش"},
    {"id": 61, "city": "مرتيل"},
    {"id": 62, "city": "مشرع بلقصيري"},
    {"id": 63, "city": "مكناس"},
    {"id": 64, "city": "وادي زم"},
    {"id": 65, "city": "وجدة"},
    {"id": 66, "city": "ورزازات"},
    {"id": 67, "city": "وزان"},
    {"id": 68, "city": "الفقيه بن صالح"},
    {"id": 69, "city": "تيفلت"},
    {"id": 70, "city": "سيدي سليمان"},
    {"id": 71, "city": "الرشيدية"},
    {"id": 72, "city": "بوعرفة"},
    {"id": 73, "city": "ميدلت"},
    {"id": 74, "city": "الريش"},
    {"id": 75, "city": "كرسيف"},
    {"id": 76, "city": "تاهلة"},
    {"id": 77, "city": "مديونة"},
    {"id": 78, "city": "بنسليمان"},
    {"id": 79, "city": "تيط مليل"},
    {"id": 80, "city": "المديق"},
    {"id": 81, "city": "الفنيدق"},
    {"id": 82, "city": "مارتيل"},
    {"id": 83, "city": "أزرو"},
    {"id": 84, "city": "الحاجب"},
    {"id": 85, "city": "تاوريرت"},
    {"id": 86, "city": "جرادة"},
    {"id": 87, "city": "بوعرفة"},
    {"id": 88, "city": "دبدو"},
    {"id": 89, "city": "عين بني مطهر"},
    {"id": 90, "city": "سلوان"},
    {"id": 91, "city": "زايو"},
    {"id": 92, "city": "بني انصار"},
    {"id": 93, "city": "الدريوش"},
    {"id": 94, "city": "ميضار"},
    {"id": 95, "city": "بن الطيب"},
    {"id": 96, "city": "امزورن"},
    {"id": 97, "city": "تارجيست"},
    {"id": 98, "city": "بني بوعياش"},
    {"id": 99, "city": "إمزورن"},
    {"id": 100, "city": "أجدير"},
    {"id": 101, "city": "واد لاو"},
    {"id": 102, "city": "زوارة"},
    {"id": 103, "city": "بني حسان"},
    {"id": 104, "city": "أزلا"},
    {"id": 105, "city": "مقريصات"},
    {"id": 106, "city": "سبتة"},
    {"id": 107, "city": "القصر الصغير"},
    {"id": 108, "city": "خميس الساحل"},
    {"id": 109, "city": "سيدي اليماني"},
    {"id": 110, "city": "مولاي بوسلهام"},
    {"id": 111, "city": "سوق الاربعاء"},
    {"id": 112, "city": "عين العودة"},
    {"id": 113, "city": "سيدي علال البحراوي"},
    {"id": 114, "city": "سيدي يحيى زعير"},
    {"id": 115, "city": "عين عتيق"},
    {"id": 116, "city": "تيداس"},
    {"id": 117, "city": "سيدي بطاش"},
    {"id": 118, "city": "الهرهورة"},
    {"id": 119, "city": "عين الذئاب"},
    {"id": 120, "city": "بوسكورة"},
    {"id": 121, "city": "دار بوعزة"},
    {"id": 122, "city": "النواصر"},
    {"id": 123, "city": "بوزنيقة"},
    {"id": 124, "city": "المنصورية"},
    {"id": 125, "city": "بنسليمان"},
    {"id": 126, "city": "بوزنيقة"},
    {"id": 127, "city": "الشلالات"},
    {"id": 128, "city": "سيدي رحال"},
    {"id": 129, "city": "حد السوالم"},
    {"id": 130, "city": "الدروة"},
    {"id": 131, "city": "بن احمد"},
    {"id": 132, "city": "سطات"},
    {"id": 133, "city": "البروج"},
    {"id": 134, "city": "لولاد"},
    {"id": 135, "city": "خريبكة"},
    {"id": 136, "city": "وادي زم"},
    {"id": 137, "city": "أبي الجعد"},
    {"id": 138, "city": "بني ملال"},
    {"id": 139, "city": "القصيبة"},
    {"id": 140, "city": "زاوية الشيخ"},
    {"id": 141, "city": "سوق السبت أولاد النمة"},
    {"id": 142, "city": "الفقيه بن صالح"},
    {"id": 143, "city": "دمنات"},
    {"id": 144, "city": "أزيلال"},
    {"id": 145, "city": "واويزغت"},
    {"id": 146, "city": "بزو"},
    {"id": 147, "city": "تنغير"},
    {"id": 148, "city": "قلعة مكونة"},
    {"id": 149, "city": "بومالن دادس"},
    {"id": 150, "city": "ورزازات"},
    {"id": 151, "city": "زاكورة"},
    {"id": 152, "city": "أكدز"},
    {"id": 153, "city": "تنزولين"},
    {"id": 154, "city": "تارودانت"},
    {"id": 155, "city": "أولاد برحيل"},
    {"id": 156, "city": "إيغرم"},
    {"id": 157, "city": "تالوين"},
    {"id": 158, "city": "تزنيت"},
    {"id": 159, "city": "أكلو"},
    {"id": 160, "city": "سيدي إفني"},
    {"id": 161, "city": "كلميم"},
    {"id": 162, "city": "بويزكارن"},
    {"id": 163, "city": "طانطان"},
    {"id": 164, "city": "طرفاية"},
    {"id": 165, "city": "العيون"},
    {"id": 166, "city": "المرسى"},
    {"id": 167, "city": "بوجدور"},
    {"id": 168, "city": "طرفاية"},
    {"id": 169, "city": "السمارة"},
    {"id": 170, "city": "الداخلة"},
    {"id": 171, "city": "العركوب"},
    {"id": 172, "city": "بئر كندوز"},
    {"id": 173, "city": "الكويرة"},
    {"id": 174, "city": "لمهيريز"},
    {"id": 175, "city": "أوسرد"},
    {"id": 176, "city": "تيشلا"},
    {"id": 177, "city": "الزاك"},
    {"id": 178, "city": "أسا"},
    {"id": 179, "city": "طاطا"},
    {"id": 180, "city": "فم زكيد"},
    {"id": 181, "city": "أقا"},
    {"id": 182, "city": "تافراوت"},
    {"id": 183, "city": "تيزنيت"},
    {"id": 184, "city": "سيدي إفني"},
    {"id": 185, "city": "بيوكرى"},
    {"id": 186, "city": "أيت باها"},
    {"id": 187, "city": "تارودانت"},
    {"id": 188, "city": "أولاد تايمة"},
    {"id": 189, "city": "إينزكان"},
    {"id": 190, "city": "الدشيرة الجهادية"},
    {"id": 191, "city": "أيت ملول"},
    {"id": 192, "city": "تمسية"},
    {"id": 193, "city": "أورير"},
    {"id": 194, "city": "تامري"},
    {"id": 195, "city": "إمي وادار"},
    {"id": 196, "city": "تافوغالت"},
    {"id": 197, "city": "أمسكرود"},
    {"id": 198, "city": "الدراركة"},
    {"id": 199, "city": "إداوتنان"},
    {"id": 200, "city": "أكادير"},
    {"id": 201, "city": "تيكوين"},
    {"id": 202, "city": "بنسركاو"},
    {"id": 203, "city": "القليعة"},
    {"id": 204, "city": "سيدي بيبي"},
    {"id": 205, "city": "أيت عميرة"},
    {"id": 206, "city": "بيوكرى"},
    {"id": 207, "city": "الصويرة"},
    {"id": 208, "city": "تمنار"},
    {"id": 209, "city": "تافتاشت"},
    {"id": 210, "city": "سيدي كاوكي"},
    {"id": 211, "city": "أيت داود"},
    {"id": 212, "city": "تالمست"},
    {"id": 213, "city": "أقرمود"},
    {"id": 214, "city": "مراكش"},
    {"id": 215, "city": "تحناوت"},
    {"id": 216, "city": "أيت أورير"}
  ]
}
